README.rst
setup.py
sdipylib/__init__.py
sdipylib/url.py
sdipylib.egg-info/PKG-INFO
sdipylib.egg-info/SOURCES.txt
sdipylib.egg-info/dependency_links.txt
sdipylib.egg-info/requires.txt
sdipylib.egg-info/top_level.txt
test/test_basic.py