Metadata-Version: 1.1
Name: sdipylib
Version: 1009
Summary: San Diego Regional Data LIbrary library for IPython data analysis
Home-page: https://github.com/sdrdl/sdipylib
Author: eric@sandiegodata.org
Author-email: eric@sandiegodata.org
License: BSD
Platform: UNKNOWN
Classifier: Development Status :: 2 - Pre-Alpha
Classifier: Environment :: Console
Classifier: Intended Audience :: Developers
Classifier: License :: OSI Approved :: BSD License
Classifier: Operating System :: OS Independent
Classifier: Programming Language :: Python
Classifier: Programming Language :: Python :: 2.6
Classifier: Programming Language :: Python :: 2.7
Classifier: Topic :: Software Development :: Libraries :: Python Modules
